onnxconverter_common/__init__.py
onnxconverter_common/_opt_const_folding.py
onnxconverter_common/auto_mixed_precision.py
onnxconverter_common/auto_mixed_precision_model_path.py
onnxconverter_common/case_insensitive_dict.py
onnxconverter_common/container.py
onnxconverter_common/data_types.py
onnxconverter_common/decast.py
onnxconverter_common/float16.py
onnxconverter_common/interface.py
onnxconverter_common/metadata_props.py
onnxconverter_common/onnx2py.py
onnxconverter_common/onnx_ex.py
onnxconverter_common/onnx_fx.py
onnxconverter_common/onnx_ops.py
onnxconverter_common/oopb.py
onnxconverter_common/optimizer.py
onnxconverter_common/perfstats.py
onnxconverter_common/pytracing.py
onnxconverter_common/registration.py
onnxconverter_common/shape_calculator.py
onnxconverter_common/topology.py
onnxconverter_common/tree_ensemble.py
onnxconverter_common/utils.py
onnxconverter_common-1.15.0.dist-info/licenses/LICENSE
onnxconverter_common-1.15.0.dist-info/licenses/NOTICE
onnxconverter_common-1.15.0.dist-info/METADATA
onnxconverter_common-1.15.0.dist-info/WHEEL
onnxconverter_common-1.15.0.dist-info/top_level.txt
onnxconverter_common-1.15.0.dist-info/RECORD
