Metadata-Version: 2.4
Name: onnxconverter-common
Version: 1.15.0
Summary: ONNX Converter and Optimization Tools
Home-page: https://github.com/microsoft/onnxconverter-common
Author: Microsoft Corporation
Author-email: Microsoft Corporation <onnx@microsoft.com>
License:     MIT License
Project-URL: Repository, https://github.com/microsoft/onnxconverter-common
Classifier: Development Status :: 5 - Production/Stable
Classifier: Environment :: Console
Classifier: Intended Audience :: Developers
Classifier: Operating System :: MacOS :: MacOS X
Classifier: Operating System :: Microsoft :: Windows
Classifier: Programming Language :: Python
Classifier: Programming Language :: Python :: 3.8
Classifier: Programming Language :: Python :: 3.9
Classifier: Programming Language :: Python :: 3.10
Classifier: Programming Language :: Python :: 3.11
Classifier: Programming Language :: Python :: 3.12
Classifier: Programming Language :: Python :: 3.13
Classifier: License :: OSI Approved :: MIT License
Requires-Python: >=3.8
License-File: LICENSE
License-File: NOTICE
Requires-Dist: numpy
Requires-Dist: onnx
Requires-Dist: packaging
Requires-Dist: protobuf>=3.20.2
Provides-Extra: test
Requires-Dist: pytest; extra == "test"
Requires-Dist: pytest-cov; extra == "test"
Provides-Extra: lint
Requires-Dist: ruff; extra == "lint"
Requires-Dist: pyright; extra == "lint"
Provides-Extra: dev
Requires-Dist: onnxconverter-common[lint,test]; extra == "dev"
Dynamic: author
Dynamic: home-page
Dynamic: license-file
